octopus_up/__init__.py
octopus_up/model_downloader.py
octopus_up/up.py
octopus_up-0.4.18.dist-info/METADATA
octopus_up-0.4.18.dist-info/WHEEL
octopus_up-0.4.18.dist-info/entry_points.txt
octopus_up-0.4.18.dist-info/top_level.txt
octopus_up-0.4.18.dist-info/RECORD
