Metadata-Version: 2.1
Name: octopus-up
Version: 0.4.18
Summary: Open source code interpreter agent for LLM
Home-page: https://github.com/dbpunk-labs/octopus
Author: imotai
Author-email: wangtaize@dbpunk.com
Requires-Dist: octopus-sdk
Requires-Dist: requests
Requires-Dist: huggingface-hub
Requires-Dist: rich
Requires-Dist: click
